namedpipe/__init__.py
namedpipe/_posix.py
namedpipe/_win32.py
namedpipe-0.3.0.dist-info/licenses/LICENSE
namedpipe-0.3.0.dist-info/METADATA
namedpipe-0.3.0.dist-info/WHEEL
namedpipe-0.3.0.dist-info/top_level.txt
namedpipe-0.3.0.dist-info/RECORD
